ttvcloud/ApiInfo.py
ttvcloud/Credentials.py
ttvcloud/Policy.py
ttvcloud/ServiceInfo.py
ttvcloud/__init__.py
ttvcloud/auth/MetaData.py
ttvcloud/auth/SignerV4.py
ttvcloud/auth/__init__.py
ttvcloud/base/Request.py
ttvcloud/base/Service.py
ttvcloud/base/__init__.py
ttvcloud/const/Const.py
ttvcloud/const/__init__.py
ttvcloud/edit/EditService.py
ttvcloud/edit/__init__.py
ttvcloud/example/__init__.py
ttvcloud/example/example_edit.py
ttvcloud/example/example_get_poster_url.py
ttvcloud/example/example_get_token.py
ttvcloud/example/example_list_users.py
ttvcloud/example/example_play.py
ttvcloud/example/example_set_video_publish_status.py
ttvcloud/example/example_start_transcode.py
ttvcloud/example/example_sts2.py
ttvcloud/example/example_upload_poster.py
ttvcloud/example/example_upload_video.py
ttvcloud/example/example_vod_sts2_play.py
ttvcloud/example/imagex/__init__.py
ttvcloud/example/imagex/example_common.py
ttvcloud/example/imagex/example_delete_image.py
ttvcloud/example/imagex/example_get_image_info.py
ttvcloud/example/imagex/example_update_image.py
ttvcloud/example/imagex/example_upload_image.py
ttvcloud/example/imagex/example_upload_image_token.py
ttvcloud/example/imagex/example_upload_sts2.py
ttvcloud/iam/IamService.py
ttvcloud/iam/__init__.py
ttvcloud/imagex/ImageXService.py
ttvcloud/imagex/__init__.py
ttvcloud/util/Util.py
ttvcloud/util/__init__.py
ttvcloud/vod/ImgUrlOption.py
ttvcloud/vod/VodService.py
ttvcloud/vod/__init__.py
ttvcloud-0.0.39.dist-info/METADATA
ttvcloud-0.0.39.dist-info/WHEEL
ttvcloud-0.0.39.dist-info/top_level.txt
ttvcloud-0.0.39.dist-info/RECORD
