Metadata-Version: 2.1
Name: ttvcloud
Version: 0.0.39
Summary: The TTvcloud SDK for Python
Home-page: https://github.com/TTvcloud/vcloud-sdk-python
Author: TTVcloud SDK
Author-email: vcloudplatform@bytedance.com
License: MIT Licence
Keywords: pip,ttvcloud,vcloud-sdk-python
Platform: any
Requires-Dist: requests
Requires-Dist: pytz
Requires-Dist: pycryptodome
